{
	"format_version": "1.8.0",
	"animations": {
		"move.walk": {
			"loop": true,
			"bones": {
				"body": {
					"position": {
						"vector": [0, "math.sin(query.anim_time*500)*0.5", 0]
					}
				},
				"tail": {
					"rotation": {
						"vector": [0, "math.sin(query.anim_time*500)*5", 0]
					},
					"position": {
						"vector": [0, "math.sin(query.anim_time*500)*0.5", 0]
					}
				},
				"left_wing": {
					"rotation": {
						"vector": ["math.sin(query.anim_time*500)*5+5", "math.sin(query.anim_time*500)*5+5", "-math.sin(query.anim_time*500)*5"]
					},
					"position": {
						"vector": [0, "math.sin(query.anim_time*500)*0.5", 0]
					}
				},
				"right_wing": {
					"rotation": {
						"vector": ["math.sin(query.anim_time*500)*5+5", "-math.sin(query.anim_time*500)*5-5", "math.sin(query.anim_time*500)*5"]
					},
					"position": {
						"vector": [0, "math.sin(query.anim_time*500)*0.5", 0]
					}
				},
				"head": {
					"rotation": {
						"vector": ["math.sin(query.anim_time*500)*5+5", 0, 0]
					},
					"position": {
						"vector": [0, "math.sin(query.anim_time*500)*0.5", 0]
					}
				},
				"left_front_leg": {
					"rotation": {
						"vector": ["math.sin(query.anim_time*500)*20", 0, 0]
					}
				},
				"right_front_leg": {
					"rotation": {
						"vector": ["-math.sin(query.anim_time*500)*20", 0, 0]
					}
				},
				"left_hind_leg": {
					"rotation": {
						"vector": ["-math.sin(query.anim_time*500)*20", 0, 0]
					}
				},
				"right_hind_leg": {
					"rotation": {
						"vector": ["math.sin(query.anim_time*500)*20", 0, 0]
					}
				}
			}
		},
		"move.fly": {
			"loop": true,
			"bones": {
				"body": {
					"position": {
						"vector": [0, "-math.cos(query.anim_time*500)*2", 0]
					}
				},
				"tail": {
					"rotation": {
						"vector": [0, "-math.cos(query.anim_time*500)*8", 0]
					},
					"position": {
						"vector": [0, "-math.cos(query.anim_time*500)*2", 0]
					}
				},
				"left_wing": {
					"rotation": {
						"vector": ["math.cos(query.anim_time*500)*20+20", "math.cos(query.anim_time*500)*15+15", "math.sin(query.anim_time*500)*10+10"]
					},
					"position": {
						"vector": [0, "-math.cos(query.anim_time*500)*2", 0]
					}
				},
				"right_wing": {
					"rotation": {
						"vector": ["math.cos(query.anim_time*500)*20+20", "-math.cos(query.anim_time*500)*15-15", "-math.sin(query.anim_time*500)*10-10"]
					},
					"position": {
						"vector": [0, "-math.cos(query.anim_time*500)*2", 0]
					}
				},
				"head": {
					"rotation": {
						"vector": ["-math.cos(query.anim_time*500)*8+8", 0, 0]
					},
					"position": {
						"vector": [0, "-math.cos(query.anim_time*500)*2", 0]
					}
				},
				"left_front_leg": {
					"rotation": {
						"vector": ["math.cos(query.anim_time*500)*8-20", 0, 0]
					},
					"position": {
						"vector": [0, "-math.cos(query.anim_time*500)*2", 0]
					}
				},
				"right_front_leg": {
					"rotation": {
						"vector": ["math.cos(query.anim_time*500)*8-20", 0, 0]
					},
					"position": {
						"vector": [0, "-math.cos(query.anim_time*500)*2", 0]
					}
				},
				"left_hind_leg": {
					"rotation": {
						"vector": ["-math.cos(query.anim_time*500)*8+20", 0, 0]
					},
					"position": {
						"vector": [0, "-math.cos(query.anim_time*500)*2", 0]
					}
				},
				"right_hind_leg": {
					"rotation": {
						"vector": ["-math.cos(query.anim_time*500)*8+20", 0, 0]
					},
					"position": {
						"vector": [0, "-math.cos(query.anim_time*500)*2", 0]
					}
				}
			}
		},
		"misc.idle": {
			"loop": true,
			"bones": {
				"tail": {
					"rotation": {
						"vector": [0, "math.sin(query.anim_time*500)*2", 0]
					}
				},
				"left_wing": {
					"rotation": {
						"vector": ["math.sin(query.anim_time*500)*2+2", 0, 0]
					}
				},
				"right_wing": {
					"rotation": {
						"vector": ["-math.sin(query.anim_time*500)*2+2", 0, 0]
					}
				},
				"head": {
					"rotation": {
						"vector": ["math.sin(query.anim_time*500)*2+2", 0, 0]
					}
				}
			}
		},
		"animation.lesser.swim": {
			"loop": true,
			"bones": {
				"body": {
					"position": {
						"vector": [0, "math.sin(query.anim_time*500)*0.5", 0]
					}
				},
				"tail": {
					"rotation": {
						"vector": [0, "math.sin(query.anim_time*500)*5", 0]
					},
					"position": {
						"vector": [0, "math.sin(query.anim_time*500)*0.5", 0]
					}
				},
				"left_wing": {
					"rotation": {
						"vector": ["math.sin(query.anim_time*500)*2+5", "math.sin(query.anim_time*500)*2+5", "-math.sin(query.anim_time*500)*2+10"]
					},
					"position": {
						"vector": [0, "math.sin(query.anim_time*500)*0.5", 0]
					}
				},
				"right_wing": {
					"rotation": {
						"vector": ["math.sin(query.anim_time*500)*2+5", "-math.sin(query.anim_time*500)*2-5", "math.sin(query.anim_time*500)*2-10"]
					},
					"position": {
						"vector": [0, "math.sin(query.anim_time*500)*0.5", 0]
					}
				},
				"head": {
					"rotation": {
						"vector": ["math.sin(query.anim_time*500)*5-10", 0, 0]
					},
					"position": {
						"vector": [0, "math.sin(query.anim_time*500)*0.5", 1]
					}
				},
				"left_front_leg": {
					"rotation": {
						"vector": ["math.sin(query.anim_time*500)*-5", 0, 0]
					}
				},
				"right_front_leg": {
					"rotation": {
						"vector": ["math.sin(query.anim_time*500)*5", 0, 0]
					}
				},
				"left_hind_leg": {
					"rotation": {
						"vector": ["-math.sin(query.anim_time*500)*5", 0, 0]
					}
				},
				"right_hind_leg": {
					"rotation": {
						"vector": ["-math.sin(query.anim_time*500)*-5", 0, 0]
					}
				}
			}
		}
	},
	"geckolib_format_version": 2
}